nexula/__init__.py
nexula/__main__.py
nexula/cli.py
nexula/nexula_controller/__init__.py
nexula/nexula_controller/controller.py
nexula/nexula_data/__init__.py
nexula/nexula_data/data_controller.py
nexula/nexula_data/data_loader.py
nexula/nexula_data/data_reader.py
nexula/nexula_exception/__init__.py
nexula/nexula_inventory/__init__.py
nexula/nexula_inventory/inventory_base.py
nexula/nexula_inventory/inventory_data_preprocesser.py
nexula/nexula_inventory/inventory_feature_representer.py
nexula/nexula_inventory/inventory_metrics.py
nexula/nexula_inventory/inventory_translator.py
nexula/nexula_inventory/inventory_callback/__init__.py
nexula/nexula_inventory/inventory_callback/callback_general.py
nexula/nexula_inventory/inventory_callback/callback_lightning.py
nexula/nexula_inventory/inventory_model/__init__.py
nexula/nexula_inventory/inventory_model/model_boomer.py
nexula/nexula_inventory/inventory_model/model_millenial.py
nexula/nexula_inventory/inventory_model/architecture_torch/__init__.py
nexula/nexula_inventory/inventory_model/architecture_torch/torch_cnn1d.py
nexula/nexula_inventory/inventory_model/architecture_torch/torch_lstm.py
nexula/nexula_inventory/inventory_model/model_millenial_helper/__init__.py
nexula/nexula_inventory/inventory_model/model_millenial_helper/helper_millenial_lightning.py
nexula/nexula_inventory/representer_torchtext/__init__.py
nexula/nexula_inventory/representer_torchtext/torchtext_helper.py
nexula/nexula_logging/__init__.py
nexula/nexula_logging/nexus_log.py
nexula/nexula_train/__init__.py
nexula/nexula_train/train_controller.py
nexula/nexula_utility/__init__.py
nexula/nexula_utility/utility_extract_func.py
nexula/nexula_utility/utility_import_var.py
nexula/nexula_utility/utility_singleton.py
nexula/nexula_utility/utility_yaml_parser.py
tests/integration_test/__init__.py
tests/integration_test/test_full_integration.py
tests/unit_test/__init__.py
tests/unit_test/data/__init__.py
tests/unit_test/data/data_reader.py
nexula-0.0.1.dist-info/METADATA
nexula-0.0.1.dist-info/WHEEL
nexula-0.0.1.dist-info/entry_points.txt
nexula-0.0.1.dist-info/top_level.txt
nexula-0.0.1.dist-info/RECORD
