Metadata-Version: 2.1
Name: nexula
Version: 0.0.1
Summary: (In development) Tools on Benchmarking Machine Learning Toolkit
Home-page: https://github.com/haryoa/nexus
Author: Haryo A W
Author-email: haryo97@gmail.com
License: MIT License
Platform: UNKNOWN
Requires-Python: >=3.6.0
Requires-Dist: joblib (==0.14.1)
Requires-Dist: scikit-learn (==0.22.2.post1)
Requires-Dist: colorlog (==4.1.0)
Requires-Dist: nltk (==3.5)
Requires-Dist: pyyaml (==5.3.1)
Requires-Dist: pandas (==1.0.1)
